{
"meta":{"test_sets":[],"test_metrics":[],"learn_metrics":[{"best_value":"Min","name":"RMSE"}],"launch_mode":"Train","parameters":"","iteration_count":383,"learn_sets":["learn"],"name":"experiment"},
"iterations":[
{"learn":[4173719.278],"iteration":0,"passed_time":0.03503523228,"remaining_time":13.38345873},
{"learn":[3965002.373],"iteration":1,"passed_time":0.06418004184,"remaining_time":12.22629797},
{"learn":[3778518.58],"iteration":2,"passed_time":0.09549070553,"remaining_time":12.09548937},
{"learn":[3617370.993],"iteration":3,"passed_time":0.1236094565,"remaining_time":11.711996},
{"learn":[3475760.636],"iteration":4,"passed_time":0.1511019013,"remaining_time":11.42330374},
{"learn":[3348687.972],"iteration":5,"passed_time":0.1793659383,"remaining_time":11.27015979},
{"learn":[3239471.089],"iteration":6,"passed_time":0.207749196,"remaining_time":11.15909967},
{"learn":[3147279.419],"iteration":7,"passed_time":0.2354078224,"remaining_time":11.03474167},
{"learn":[3059726.199],"iteration":8,"passed_time":0.2635909266,"remaining_time":10.9536674},
{"learn":[2984605.358],"iteration":9,"passed_time":0.2916432234,"remaining_time":10.87829223},
{"learn":[2919742.182],"iteration":10,"passed_time":0.3212204332,"remaining_time":10.86309101},
{"learn":[2862006.582],"iteration":11,"passed_time":0.349139144,"remaining_time":10.79421854},
{"learn":[2813287.344],"iteration":12,"passed_time":0.3754256358,"remaining_time":10.68519117},
{"learn":[2769209.715],"iteration":13,"passed_time":0.4036410029,"remaining_time":10.63882358},
{"learn":[2728145.383],"iteration":14,"passed_time":0.4311924547,"remaining_time":10.57858822},
{"learn":[2694605.187],"iteration":15,"passed_time":0.4575403329,"remaining_time":10.49483139},
{"learn":[2662701.26],"iteration":16,"passed_time":0.4848907342,"remaining_time":10.43941228},
{"learn":[2636559.882],"iteration":17,"passed_time":0.5115518963,"remaining_time":10.37313567},
{"learn":[2610807.332],"iteration":18,"passed_time":0.5386198392,"remaining_time":10.31882218},
{"learn":[2588541.65],"iteration":19,"passed_time":0.5662878373,"remaining_time":10.27812425},
{"learn":[2570377.911],"iteration":20,"passed_time":0.5939745118,"remaining_time":10.2389892},
{"learn":[2551622.548],"iteration":21,"passed_time":0.6222230759,"remaining_time":10.21011502},
{"learn":[2536524.929],"iteration":22,"passed_time":0.6504308664,"remaining_time":10.18065704},
{"learn":[2523111.942],"iteration":23,"passed_time":0.6781627949,"remaining_time":10.14418514},
{"learn":[2511536.889],"iteration":24,"passed_time":0.7056696391,"remaining_time":10.10518923},
{"learn":[2496450.407],"iteration":25,"passed_time":0.7331398243,"remaining_time":10.06657374},
{"learn":[2486245.582],"iteration":26,"passed_time":0.7602717296,"remaining_time":10.02432355},
{"learn":[2477885.425],"iteration":27,"passed_time":0.7860075969,"remaining_time":9.965453461},
{"learn":[2469227.076],"iteration":28,"passed_time":0.8136631692,"remaining_time":9.932302134},
{"learn":[2463022.861],"iteration":29,"passed_time":0.8387965867,"remaining_time":9.869839837},
{"learn":[2456906.132],"iteration":30,"passed_time":0.8651798079,"remaining_time":9.823977174},
{"learn":[2450341.046],"iteration":31,"passed_time":0.8913040904,"remaining_time":9.776491742},
{"learn":[2441649.128],"iteration":32,"passed_time":0.9190008152,"remaining_time":9.746978343},
{"learn":[2436024.515],"iteration":33,"passed_time":0.9446117827,"remaining_time":9.696162122},
{"learn":[2428191.051],"iteration":34,"passed_time":0.9727687804,"remaining_time":9.672101016},
{"learn":[2422094.705],"iteration":35,"passed_time":0.9996764404,"remaining_time":9.635770134},
{"learn":[2414779.691],"iteration":36,"passed_time":1.028800009,"remaining_time":9.620670351},
{"learn":[2409925.014],"iteration":37,"passed_time":1.056231417,"remaining_time":9.589469443},
{"learn":[2406731.156],"iteration":38,"passed_time":1.081243534,"remaining_time":9.537122453},
{"learn":[2403500.934],"iteration":39,"passed_time":1.108464838,"remaining_time":9.505085983},
{"learn":[2398973.965],"iteration":40,"passed_time":1.135862475,"remaining_time":9.474755275},
{"learn":[2395813.646],"iteration":41,"passed_time":1.160801376,"remaining_time":9.424601646},
{"learn":[2392401.571],"iteration":42,"passed_time":1.187534794,"remaining_time":9.389810003},
{"learn":[2388133.066],"iteration":43,"passed_time":1.214627141,"remaining_time":9.358150018},
{"learn":[2385532.611],"iteration":44,"passed_time":1.240630028,"remaining_time":9.318509987},
{"learn":[2381846.934],"iteration":45,"passed_time":1.266503278,"remaining_time":9.278513144},
{"learn":[2379116.619],"iteration":46,"passed_time":1.29319993,"remaining_time":9.245003757},
{"learn":[2375592.448],"iteration":47,"passed_time":1.321085257,"remaining_time":9.220074187},
{"learn":[2373260.192],"iteration":48,"passed_time":1.348337961,"remaining_time":9.190711817},
{"learn":[2370950.505],"iteration":49,"passed_time":1.376156288,"remaining_time":9.165200879},
{"learn":[2368953.188],"iteration":50,"passed_time":1.404088212,"remaining_time":9.140338946},
{"learn":[2366215.564],"iteration":51,"passed_time":1.431062051,"remaining_time":9.109260364},
{"learn":[2364041.632],"iteration":52,"passed_time":1.458007871,"remaining_time":9.078162214},
{"learn":[2361740.163],"iteration":53,"passed_time":1.483555975,"remaining_time":9.038702147},
{"learn":[2358057.688],"iteration":54,"passed_time":1.511100154,"remaining_time":9.011651829},
{"learn":[2356459.604],"iteration":55,"passed_time":1.536902466,"remaining_time":8.974412612},
{"learn":[2354393.22],"iteration":56,"passed_time":1.56431322,"remaining_time":8.946773855},
{"learn":[2352986.129],"iteration":57,"passed_time":1.591409121,"remaining_time":8.917378694},
{"learn":[2351079.722],"iteration":58,"passed_time":1.618588057,"remaining_time":8.888517467},
{"learn":[2347957.162],"iteration":59,"passed_time":1.646474258,"remaining_time":8.863519753},
{"learn":[2346467.582],"iteration":60,"passed_time":1.671927649,"remaining_time":8.825585297},
{"learn":[2345260.194],"iteration":61,"passed_time":1.697315902,"remaining_time":8.787716204},
{"learn":[2344138.451],"iteration":62,"passed_time":1.722756779,"remaining_time":8.750510624},
{"learn":[2343243.201],"iteration":63,"passed_time":1.749542637,"remaining_time":8.720376579},
{"learn":[2340558.174],"iteration":64,"passed_time":1.776975261,"remaining_time":8.693509736},
{"learn":[2339470.308],"iteration":65,"passed_time":1.802340681,"remaining_time":8.656696909},
{"learn":[2338762.845],"iteration":66,"passed_time":1.827321249,"remaining_time":8.618410668},
{"learn":[2337564.003],"iteration":67,"passed_time":1.855159502,"remaining_time":8.593753577},
{"learn":[2336554.665],"iteration":68,"passed_time":1.882142134,"remaining_time":8.565110582},
{"learn":[2334889.729],"iteration":69,"passed_time":1.909821162,"remaining_time":8.53962891},
{"learn":[2333476.872],"iteration":70,"passed_time":1.937321987,"remaining_time":8.513302254},
{"learn":[2331542.533],"iteration":71,"passed_time":1.964229241,"remaining_time":8.484379084},
{"learn":[2330951.715],"iteration":72,"passed_time":1.991569999,"remaining_time":8.457352052},
{"learn":[2329847.284],"iteration":73,"passed_time":2.018858933,"remaining_time":8.430100139},
{"learn":[2328493.42],"iteration":74,"passed_time":2.046839075,"remaining_time":8.405685802},
{"learn":[2327585.165],"iteration":75,"passed_time":2.072360243,"remaining_time":8.371244667},
{"learn":[2326873.86],"iteration":76,"passed_time":2.098155981,"remaining_time":8.338126364},
{"learn":[2324673.414],"iteration":77,"passed_time":2.126168853,"remaining_time":8.313865386},
{"learn":[2323588.185],"iteration":78,"passed_time":2.153642305,"remaining_time":8.287433679},
{"learn":[2322392.477],"iteration":79,"passed_time":2.180233594,"remaining_time":8.257634736},
{"learn":[2321749.085],"iteration":80,"passed_time":2.206055794,"remaining_time":8.225047529},
{"learn":[2321050.548],"iteration":81,"passed_time":2.233187843,"remaining_time":8.197433423},
{"learn":[2320394.614],"iteration":82,"passed_time":2.258677849,"remaining_time":8.163895839},
{"learn":[2319668.1],"iteration":83,"passed_time":2.286284752,"remaining_time":8.13808501},
{"learn":[2317806.446],"iteration":84,"passed_time":2.313722119,"remaining_time":8.111637547},
{"learn":[2316734.89],"iteration":85,"passed_time":2.339881705,"remaining_time":8.080754262},
{"learn":[2316025.791],"iteration":86,"passed_time":2.365868454,"remaining_time":8.049391521},
{"learn":[2315548.516],"iteration":87,"passed_time":2.392732369,"remaining_time":8.021091466},
{"learn":[2314544.378],"iteration":88,"passed_time":2.41905076,"remaining_time":7.991021612},
{"learn":[2313173.933],"iteration":89,"passed_time":2.445393877,"remaining_time":7.961115623},
{"learn":[2312295.68],"iteration":90,"passed_time":2.473013152,"remaining_time":7.93538286},
{"learn":[2310609.061],"iteration":91,"passed_time":2.499902456,"remaining_time":7.90730016},
{"learn":[2310233.017],"iteration":92,"passed_time":2.525033423,"remaining_time":7.873760135},
{"learn":[2308692.933],"iteration":93,"passed_time":2.553178435,"remaining_time":7.849665613},
{"learn":[2307792.434],"iteration":94,"passed_time":2.577831344,"remaining_time":7.814899233},
{"learn":[2306772.871],"iteration":95,"passed_time":2.604976107,"remaining_time":7.787793154},
{"learn":[2306158.16],"iteration":96,"passed_time":2.631775901,"remaining_time":7.759669152},
{"learn":[2304919.866],"iteration":97,"passed_time":2.659690616,"remaining_time":7.734814546},
{"learn":[2304306.316],"iteration":98,"passed_time":2.685653982,"remaining_time":7.704300312},
{"learn":[2303351.394],"iteration":99,"passed_time":2.711696209,"remaining_time":7.674100271},
{"learn":[2302534.716],"iteration":100,"passed_time":2.738177921,"remaining_time":7.64520964},
{"learn":[2301559.854],"iteration":101,"passed_time":2.7653677,"remaining_time":7.6183169},
{"learn":[2300110.707],"iteration":102,"passed_time":2.793369819,"remaining_time":7.593626691},
{"learn":[2299197.325],"iteration":103,"passed_time":2.820204589,"remaining_time":7.565741156},
{"learn":[2297920.344],"iteration":104,"passed_time":2.84785373,"remaining_time":7.54003178},
{"learn":[2296821.849],"iteration":105,"passed_time":2.87540097,"remaining_time":7.514019516},
{"learn":[2295303.116],"iteration":106,"passed_time":2.902891004,"remaining_time":7.487831001},
{"learn":[2294204.548],"iteration":107,"passed_time":2.928263127,"remaining_time":7.456225556},
{"learn":[2293519.321],"iteration":108,"passed_time":2.953270606,"remaining_time":7.423817853},
{"learn":[2292716.294],"iteration":109,"passed_time":2.978893104,"remaining_time":7.393071067},
{"learn":[2292042.257],"iteration":110,"passed_time":3.005723703,"remaining_time":7.365377002},
{"learn":[2291238.71],"iteration":111,"passed_time":3.031210059,"remaining_time":7.334445767},
{"learn":[2290391.306],"iteration":112,"passed_time":3.057339489,"remaining_time":7.305147452},
{"learn":[2289299.436],"iteration":113,"passed_time":3.084535871,"remaining_time":7.278422362},
{"learn":[2287608.422],"iteration":114,"passed_time":3.112329015,"remaining_time":7.253079792},
{"learn":[2287304.789],"iteration":115,"passed_time":3.13802604,"remaining_time":7.222870281},
{"learn":[2285876.453],"iteration":116,"passed_time":3.166560933,"remaining_time":7.199189814},
{"learn":[2285064.197],"iteration":117,"passed_time":3.192659178,"remaining_time":7.169954934},
{"learn":[2284343.497],"iteration":118,"passed_time":3.217157873,"remaining_time":7.137224189},
{"learn":[2283217.214],"iteration":119,"passed_time":3.244474521,"remaining_time":7.110806658},
{"learn":[2282002.143],"iteration":120,"passed_time":3.271443077,"remaining_time":7.083620547},
{"learn":[2281088.129],"iteration":121,"passed_time":3.298434281,"remaining_time":7.056486454},
{"learn":[2280654.934],"iteration":122,"passed_time":3.323280536,"remaining_time":7.024820646},
{"learn":[2279053.274],"iteration":123,"passed_time":3.350217487,"remaining_time":6.997631687},
{"learn":[2278123.529],"iteration":124,"passed_time":3.376980434,"remaining_time":6.970087615},
{"learn":[2277086.475],"iteration":125,"passed_time":3.403117138,"remaining_time":6.941278606},
{"learn":[2276332.052],"iteration":126,"passed_time":3.430105042,"remaining_time":6.914227486},
{"learn":[2274825.315],"iteration":127,"passed_time":3.457809578,"remaining_time":6.888605018},
{"learn":[2274317.581],"iteration":128,"passed_time":3.483872515,"remaining_time":6.859717975},
{"learn":[2273214.185],"iteration":129,"passed_time":3.510382853,"remaining_time":6.831745091},
{"learn":[2272312.367],"iteration":130,"passed_time":3.537293592,"remaining_time":6.804564773},
{"learn":[2271751.93],"iteration":131,"passed_time":3.563337636,"remaining_time":6.775740504},
{"learn":[2271163.612],"iteration":132,"passed_time":3.588843403,"remaining_time":6.745946246},
{"learn":[2270539.573],"iteration":133,"passed_time":3.615303078,"remaining_time":6.717988555},
{"learn":[2269501.045],"iteration":134,"passed_time":3.641876507,"remaining_time":6.690262028},
{"learn":[2268470.04],"iteration":135,"passed_time":3.668916198,"remaining_time":6.663399271},
{"learn":[2267688.499],"iteration":136,"passed_time":3.694471383,"remaining_time":6.633868322},
{"learn":[2267183.418],"iteration":137,"passed_time":3.718942787,"remaining_time":6.60247089},
{"learn":[2266483.864],"iteration":138,"passed_time":3.744951699,"remaining_time":6.573872047},
{"learn":[2265985.401],"iteration":139,"passed_time":3.784308967,"remaining_time":6.568479136},
{"learn":[2265265.606],"iteration":140,"passed_time":3.814344479,"remaining_time":6.546605418},
{"learn":[2264464.937],"iteration":141,"passed_time":3.842524543,"remaining_time":6.521467711},
{"learn":[2263554.49],"iteration":142,"passed_time":3.869287346,"remaining_time":6.493908833},
{"learn":[2262655.77],"iteration":143,"passed_time":3.896216869,"remaining_time":6.46663772},
{"learn":[2262152.864],"iteration":144,"passed_time":3.925162202,"remaining_time":6.442680028},
{"learn":[2260836.01],"iteration":145,"passed_time":3.951467687,"remaining_time":6.414368779},
{"learn":[2259860.216],"iteration":146,"passed_time":3.977404548,"remaining_time":6.385493016},
{"learn":[2259497.465],"iteration":147,"passed_time":4.003106168,"remaining_time":6.356283443},
{"learn":[2258830.027],"iteration":148,"passed_time":4.030336708,"remaining_time":6.329522079},
{"learn":[2258194.685],"iteration":149,"passed_time":4.05604873,"remaining_time":6.300395694},
{"learn":[2257723.616],"iteration":150,"passed_time":4.082398839,"remaining_time":6.272294905},
{"learn":[2256998.743],"iteration":151,"passed_time":4.107726686,"remaining_time":6.242663583},
{"learn":[2256825.397],"iteration":152,"passed_time":4.135217396,"remaining_time":6.216339877},
{"learn":[2255993.356],"iteration":153,"passed_time":4.161088225,"remaining_time":6.18759223},
{"learn":[2255315.934],"iteration":154,"passed_time":4.190892243,"remaining_time":6.164667299},
{"learn":[2254286.245],"iteration":155,"passed_time":4.217169026,"remaining_time":6.136521595},
{"learn":[2253738.874],"iteration":156,"passed_time":4.243532841,"remaining_time":6.108524981},
{"learn":[2253303.66],"iteration":157,"passed_time":4.269074393,"remaining_time":6.079378091},
{"learn":[2251948.317],"iteration":158,"passed_time":4.296954033,"remaining_time":6.053570461},
{"learn":[2251809.604],"iteration":159,"passed_time":4.321273698,"remaining_time":6.022775217},
{"learn":[2250981.731],"iteration":160,"passed_time":4.347015178,"remaining_time":5.994020929},
{"learn":[2250801.216],"iteration":161,"passed_time":4.371264303,"remaining_time":5.963267969},
{"learn":[2250059.809],"iteration":162,"passed_time":4.399590329,"remaining_time":5.938097377},
{"learn":[2248757.295],"iteration":163,"passed_time":4.425888449,"remaining_time":5.910180307},
{"learn":[2248247.495],"iteration":164,"passed_time":4.451314641,"remaining_time":5.881130859},
{"learn":[2247278.579],"iteration":165,"passed_time":4.477437342,"remaining_time":5.853035561},
{"learn":[2246733.34],"iteration":166,"passed_time":4.508168374,"remaining_time":5.830924364},
{"learn":[2246133.171],"iteration":167,"passed_time":4.533149375,"remaining_time":5.801351879},
{"learn":[2245408.371],"iteration":168,"passed_time":4.559529346,"remaining_time":5.773605207},
{"learn":[2244357.974],"iteration":169,"passed_time":4.586775541,"remaining_time":5.746959943},
{"learn":[2243594.445],"iteration":170,"passed_time":4.613127606,"remaining_time":5.719199138},
{"learn":[2243357.902],"iteration":171,"passed_time":4.638908436,"remaining_time":5.690753953},
{"learn":[2242676.353],"iteration":172,"passed_time":4.665135756,"remaining_time":5.662881553},
{"learn":[2241794.081],"iteration":173,"passed_time":4.692456056,"remaining_time":5.636340895},
{"learn":[2241030.026],"iteration":174,"passed_time":4.719480938,"remaining_time":5.609440201},
{"learn":[2240067.531],"iteration":175,"passed_time":4.746851781,"remaining_time":5.582944992},
{"learn":[2239255.597],"iteration":176,"passed_time":4.774414375,"remaining_time":5.556663058},
{"learn":[2238720.556],"iteration":177,"passed_time":4.800868276,"remaining_time":5.529089869},
{"learn":[2238177.251],"iteration":178,"passed_time":4.826550209,"remaining_time":5.5006494},
{"learn":[2237132.017],"iteration":179,"passed_time":4.854144943,"remaining_time":5.474396797},
{"learn":[2237056.399],"iteration":180,"passed_time":4.879206195,"remaining_time":5.445301941},
{"learn":[2236100.868],"iteration":181,"passed_time":4.907002264,"remaining_time":5.419271731},
{"learn":[2235467.915],"iteration":182,"passed_time":4.933554199,"remaining_time":5.391862512},
{"learn":[2235125.353],"iteration":183,"passed_time":4.958286505,"remaining_time":5.362494644},
{"learn":[2234723.452],"iteration":184,"passed_time":4.983752804,"remaining_time":5.333962461},
{"learn":[2234150.231],"iteration":185,"passed_time":5.011065018,"remaining_time":5.307418326},
{"learn":[2233450.319],"iteration":186,"passed_time":5.03702665,"remaining_time":5.279450393},
{"learn":[2233157.682],"iteration":187,"passed_time":5.06328575,"remaining_time":5.251812348},
{"learn":[2232736.705],"iteration":188,"passed_time":5.088598452,"remaining_time":5.223217459},
{"learn":[2232310.261],"iteration":189,"passed_time":5.113802746,"remaining_time":5.194547},
{"learn":[2231553.361],"iteration":190,"passed_time":5.139653226,"remaining_time":5.166562405},
{"learn":[2231088.507],"iteration":191,"passed_time":5.164960718,"remaining_time":5.138059881},
{"learn":[2229808.481],"iteration":192,"passed_time":5.192357281,"remaining_time":5.111647064},
{"learn":[2229384.783],"iteration":193,"passed_time":5.217543429,"remaining_time":5.08307066},
{"learn":[2229011.434],"iteration":194,"passed_time":5.243370072,"remaining_time":5.055146531},
{"learn":[2228597.039],"iteration":195,"passed_time":5.269201571,"remaining_time":5.027248437},
{"learn":[2227971.803],"iteration":196,"passed_time":5.294620689,"remaining_time":4.99898197},
{"learn":[2226827.234],"iteration":197,"passed_time":5.321826934,"remaining_time":4.972414054},
{"learn":[2225936.624],"iteration":198,"passed_time":5.348682875,"remaining_time":4.945515824},
{"learn":[2224900.661],"iteration":199,"passed_time":5.376101716,"remaining_time":4.91913307},
{"learn":[2223866.062],"iteration":200,"passed_time":5.403713273,"remaining_time":4.892914506},
{"learn":[2223240.056],"iteration":201,"passed_time":5.429299514,"remaining_time":4.864867387},
{"learn":[2222613.584],"iteration":202,"passed_time":5.45670998,"remaining_time":4.838462051},
{"learn":[2221740.154],"iteration":203,"passed_time":5.484648174,"remaining_time":4.812509917},
{"learn":[2220947.528],"iteration":204,"passed_time":5.511049338,"remaining_time":4.785203815},
{"learn":[2220896.487],"iteration":205,"passed_time":5.535394569,"remaining_time":4.756139993},
{"learn":[2220406.994],"iteration":206,"passed_time":5.561961901,"remaining_time":4.729011085},
{"learn":[2219861.376],"iteration":207,"passed_time":5.588261246,"remaining_time":4.701662106},
{"learn":[2219239.032],"iteration":208,"passed_time":5.615277085,"remaining_time":4.674919678},
{"learn":[2218393.985],"iteration":209,"passed_time":5.64275449,"remaining_time":4.648554889},
{"learn":[2217918.181],"iteration":210,"passed_time":5.669735829,"remaining_time":4.621775178},
{"learn":[2217360.615],"iteration":211,"passed_time":5.695957326,"remaining_time":4.594380673},
{"learn":[2216493.174],"iteration":212,"passed_time":5.72181132,"remaining_time":4.56670387},
{"learn":[2215970.872],"iteration":213,"passed_time":5.748299511,"remaining_time":4.539544941},
{"learn":[2215376.573],"iteration":214,"passed_time":5.772783478,"remaining_time":4.51082616},
{"learn":[2214948.809],"iteration":215,"passed_time":5.797007219,"remaining_time":4.481945396},
{"learn":[2214421.007],"iteration":216,"passed_time":5.823094906,"remaining_time":4.45453343},
{"learn":[2213746.825],"iteration":217,"passed_time":5.849162703,"remaining_time":4.42711856},
{"learn":[2213407.383],"iteration":218,"passed_time":5.873862222,"remaining_time":4.398691344},
{"learn":[2212629.149],"iteration":219,"passed_time":5.901378268,"remaining_time":4.372384807},
{"learn":[2212356.384],"iteration":220,"passed_time":5.928672144,"remaining_time":4.345904467},
{"learn":[2211508.528],"iteration":221,"passed_time":5.955568408,"remaining_time":4.31912844},
{"learn":[2211374.24],"iteration":222,"passed_time":5.981705117,"remaining_time":4.291806362},
{"learn":[2210760.121],"iteration":223,"passed_time":6.007789594,"remaining_time":4.264457792},
{"learn":[2210034.938],"iteration":224,"passed_time":6.034636055,"remaining_time":4.237655541},
{"learn":[2209246.647],"iteration":225,"passed_time":6.063387251,"remaining_time":4.212176099},
{"learn":[2208511.927],"iteration":226,"passed_time":6.088823369,"remaining_time":4.184389628},
{"learn":[2207796.132],"iteration":227,"passed_time":6.114160163,"remaining_time":4.156556251},
{"learn":[2207099.709],"iteration":228,"passed_time":6.142878058,"remaining_time":4.131018432},
{"learn":[2206567.739],"iteration":229,"passed_time":6.168074739,"remaining_time":4.103110587},
{"learn":[2205798.301],"iteration":230,"passed_time":6.192881525,"remaining_time":4.074969662},
{"learn":[2205184.574],"iteration":231,"passed_time":6.219508245,"remaining_time":4.048042005},
{"learn":[2203663.352],"iteration":232,"passed_time":6.249216488,"remaining_time":4.023100744},
{"learn":[2203305.994],"iteration":233,"passed_time":6.275389311,"remaining_time":3.995867553},
{"learn":[2202533.665],"iteration":234,"passed_time":6.302191814,"remaining_time":3.969039951},
{"learn":[2202489.159],"iteration":235,"passed_time":6.32583304,"remaining_time":3.940243461},
{"learn":[2201960.377],"iteration":236,"passed_time":6.351417123,"remaining_time":3.912687342},
{"learn":[2201925.565],"iteration":237,"passed_time":6.374965131,"remaining_time":3.883907328},
{"learn":[2201258.435],"iteration":238,"passed_time":6.401221051,"remaining_time":3.856802642},
{"learn":[2200389.02],"iteration":239,"passed_time":6.428597052,"remaining_time":3.83037241},
{"learn":[2199363.129],"iteration":240,"passed_time":6.455019799,"remaining_time":3.803372662},
{"learn":[2198695.036],"iteration":241,"passed_time":6.480310232,"remaining_time":3.775717945},
{"learn":[2198087.607],"iteration":242,"passed_time":6.506147411,"remaining_time":3.748397685},
{"learn":[2197613.759],"iteration":243,"passed_time":6.532348719,"remaining_time":3.721297016},
{"learn":[2196910.25],"iteration":244,"passed_time":6.559305366,"remaining_time":3.694629145},
{"learn":[2196551.877],"iteration":245,"passed_time":6.585344201,"remaining_time":3.667447787},
{"learn":[2195868.582],"iteration":246,"passed_time":6.611822619,"remaining_time":3.640517717},
{"learn":[2195214.831],"iteration":247,"passed_time":6.636885894,"remaining_time":3.61282095},
{"learn":[2194636.519],"iteration":248,"passed_time":6.662390687,"remaining_time":3.58538294},
{"learn":[2193974.95],"iteration":249,"passed_time":6.689013709,"remaining_time":3.558555293},
{"learn":[2193318.769],"iteration":250,"passed_time":6.71619715,"remaining_time":3.532023999},
{"learn":[2192637.234],"iteration":251,"passed_time":6.743167366,"remaining_time":3.505376687},
{"learn":[2192211.085],"iteration":252,"passed_time":6.768405558,"remaining_time":3.477836848},
{"learn":[2191989.761],"iteration":253,"passed_time":6.792622769,"remaining_time":3.449796603},
{"learn":[2190858.544],"iteration":254,"passed_time":6.821491654,"remaining_time":3.424121301},
{"learn":[2190254.728],"iteration":255,"passed_time":6.846992039,"remaining_time":3.396749957},
{"learn":[2189594.538],"iteration":256,"passed_time":6.873158471,"remaining_time":3.369719717},
{"learn":[2189388.393],"iteration":257,"passed_time":6.898274339,"remaining_time":3.34218718},
{"learn":[2188852.765],"iteration":258,"passed_time":6.923659047,"remaining_time":3.314802015},
{"learn":[2188323.077],"iteration":259,"passed_time":6.949517433,"remaining_time":3.287656324},
{"learn":[2187308.377],"iteration":260,"passed_time":6.977530853,"remaining_time":3.261527832},
{"learn":[2186624.098],"iteration":261,"passed_time":7.004184398,"remaining_time":3.234756917},
{"learn":[2186137.122],"iteration":262,"passed_time":7.030461875,"remaining_time":3.207815304},
{"learn":[2185338.641],"iteration":263,"passed_time":7.05587201,"remaining_time":3.180487762},
{"learn":[2184476.871],"iteration":264,"passed_time":7.08242486,"remaining_time":3.153683523},
{"learn":[2183917.831],"iteration":265,"passed_time":7.108716161,"remaining_time":3.126766131},
{"learn":[2182843.133],"iteration":266,"passed_time":7.137137977,"remaining_time":3.100779046},
{"learn":[2182169.137],"iteration":267,"passed_time":7.162443095,"remaining_time":3.073436403},
{"learn":[2181528.079],"iteration":268,"passed_time":7.1882599,"remaining_time":3.046325757},
{"learn":[2180881.57],"iteration":269,"passed_time":7.215064823,"remaining_time":3.019638241},
{"learn":[2180845.22],"iteration":270,"passed_time":7.240100885,"remaining_time":2.992218816},
{"learn":[2180031.127],"iteration":271,"passed_time":7.266952677,"remaining_time":2.965557894},
{"learn":[2179492.108],"iteration":272,"passed_time":7.292593368,"remaining_time":2.938407584},
{"learn":[2178741.529],"iteration":273,"passed_time":7.319877771,"remaining_time":2.911922179},
{"learn":[2178431.319],"iteration":274,"passed_time":7.344925913,"remaining_time":2.884552722},
{"learn":[2177708.12],"iteration":275,"passed_time":7.370971387,"remaining_time":2.857586733},
{"learn":[2176865.29],"iteration":276,"passed_time":7.398369268,"remaining_time":2.831144919},
{"learn":[2176172.668],"iteration":277,"passed_time":7.425478372,"remaining_time":2.804587155},
{"learn":[2175418.662],"iteration":278,"passed_time":7.452658855,"remaining_time":2.778052046},
{"learn":[2175000.268],"iteration":279,"passed_time":7.478770016,"remaining_time":2.75111897},
{"learn":[2174304.547],"iteration":280,"passed_time":7.504116772,"remaining_time":2.723914273},
{"learn":[2173653.678],"iteration":281,"passed_time":7.530946472,"remaining_time":2.697253878},
{"learn":[2172674.155],"iteration":282,"passed_time":7.558242779,"remaining_time":2.670757166},
{"learn":[2171690.034],"iteration":283,"passed_time":7.585933643,"remaining_time":2.644392362},
{"learn":[2171230.16],"iteration":284,"passed_time":7.612671804,"remaining_time":2.617690655},
{"learn":[2170887.253],"iteration":285,"passed_time":7.638187115,"remaining_time":2.590573951},
{"learn":[2169869.28],"iteration":286,"passed_time":7.665592426,"remaining_time":2.564100603},
{"learn":[2169210.061],"iteration":287,"passed_time":7.693036868,"remaining_time":2.537633689},
{"learn":[2168738.393],"iteration":288,"passed_time":7.725790358,"remaining_time":2.512886829},
{"learn":[2167662.694],"iteration":289,"passed_time":7.754287376,"remaining_time":2.486719745},
{"learn":[2167198.727],"iteration":290,"passed_time":7.781724226,"remaining_time":2.460201473},
{"learn":[2166114.795],"iteration":291,"passed_time":7.809989123,"remaining_time":2.433934966},
{"learn":[2165509.594],"iteration":292,"passed_time":7.837673288,"remaining_time":2.407476437},
{"learn":[2165065.897],"iteration":293,"passed_time":7.863682201,"remaining_time":2.380502435},
{"learn":[2164997.706],"iteration":294,"passed_time":7.888480672,"remaining_time":2.353173895},
{"learn":[2164413.503],"iteration":295,"passed_time":7.915283754,"remaining_time":2.326451644},
{"learn":[2163777.975],"iteration":296,"passed_time":7.942204239,"remaining_time":2.299762843},
{"learn":[2163225.985],"iteration":297,"passed_time":7.970126804,"remaining_time":2.273358317},
{"learn":[2162237.53],"iteration":298,"passed_time":7.998124763,"remaining_time":2.246964816},
{"learn":[2161340.493],"iteration":299,"passed_time":8.024850895,"remaining_time":2.220208748},
{"learn":[2161108.642],"iteration":300,"passed_time":8.050544805,"remaining_time":2.193171674},
{"learn":[2160228.033],"iteration":301,"passed_time":8.078934937,"remaining_time":2.166866655},
{"learn":[2159530.88],"iteration":302,"passed_time":8.106928062,"remaining_time":2.140443053},
{"learn":[2158926.023],"iteration":303,"passed_time":8.133883851,"remaining_time":2.113739553},
{"learn":[2158173.532],"iteration":304,"passed_time":8.160919996,"remaining_time":2.08705495},
{"learn":[2157572.348],"iteration":305,"passed_time":8.186286586,"remaining_time":2.059947932},
{"learn":[2156753.248],"iteration":306,"passed_time":8.214657323,"remaining_time":2.03359595},
{"learn":[2156291.047],"iteration":307,"passed_time":8.242374222,"remaining_time":2.007071645},
{"learn":[2155802.174],"iteration":308,"passed_time":8.269527382,"remaining_time":1.980404616},
{"learn":[2155323.82],"iteration":309,"passed_time":8.295029433,"remaining_time":1.953345641},
{"learn":[2154838.497],"iteration":310,"passed_time":8.321441212,"remaining_time":1.92650729},
{"learn":[2154012.986],"iteration":311,"passed_time":8.34801861,"remaining_time":1.899709363},
{"learn":[2153519.026],"iteration":312,"passed_time":8.3726144,"remaining_time":1.872469674},
{"learn":[2152681.279],"iteration":313,"passed_time":8.400559823,"remaining_time":1.845982891},
{"learn":[2152030.909],"iteration":314,"passed_time":8.428616929,"remaining_time":1.819510956},
{"learn":[2151167.111],"iteration":315,"passed_time":8.45621365,"remaining_time":1.792931375},
{"learn":[2150723.666],"iteration":316,"passed_time":8.481591124,"remaining_time":1.765883326},
{"learn":[2149980.076],"iteration":317,"passed_time":8.507524839,"remaining_time":1.73895948},
{"learn":[2149458.308],"iteration":318,"passed_time":8.534127325,"remaining_time":1.712176015},
{"learn":[2148696.242],"iteration":319,"passed_time":8.560155958,"remaining_time":1.685280704},
{"learn":[2148165.877],"iteration":320,"passed_time":8.585459377,"remaining_time":1.658250721},
{"learn":[2147497.736],"iteration":321,"passed_time":8.611684386,"remaining_time":1.631406048},
{"learn":[2146979.266],"iteration":322,"passed_time":8.638291662,"remaining_time":1.604636222},
{"learn":[2146377.592],"iteration":323,"passed_time":8.664090757,"remaining_time":1.577720231},
{"learn":[2145677.366],"iteration":324,"passed_time":8.690046296,"remaining_time":1.550839031},
{"learn":[2145002.533],"iteration":325,"passed_time":8.717235905,"remaining_time":1.524179284},
{"learn":[2144101.177],"iteration":326,"passed_time":8.745608023,"remaining_time":1.497718805},
{"learn":[2143268.391],"iteration":327,"passed_time":8.771751648,"remaining_time":1.47087299},
{"learn":[2143021.804],"iteration":328,"passed_time":8.796433728,"remaining_time":1.443791554},
{"learn":[2142468.455],"iteration":329,"passed_time":8.822150765,"remaining_time":1.41689088},
{"learn":[2141723.153],"iteration":330,"passed_time":8.848224306,"remaining_time":1.390053365},
{"learn":[2140912.831],"iteration":331,"passed_time":8.876380882,"remaining_time":1.363540437},
{"learn":[2140532.157],"iteration":332,"passed_time":8.902310799,"remaining_time":1.336683303},
{"learn":[2140227.211],"iteration":333,"passed_time":8.928630889,"remaining_time":1.309888963},
{"learn":[2139883.948],"iteration":334,"passed_time":8.953587408,"remaining_time":1.282902076},
{"learn":[2139540.643],"iteration":335,"passed_time":8.978658472,"remaining_time":1.255943298},
{"learn":[2139357.254],"iteration":336,"passed_time":9.004126405,"remaining_time":1.229049895},
{"learn":[2138760.752],"iteration":337,"passed_time":9.030212875,"remaining_time":1.202247276},
{"learn":[2138580.935],"iteration":338,"passed_time":9.054272561,"remaining_time":1.175185819},
{"learn":[2138243.201],"iteration":339,"passed_time":9.079525828,"remaining_time":1.148292972},
{"learn":[2137887.19],"iteration":340,"passed_time":9.106747584,"remaining_time":1.121652195},
{"learn":[2137529.723],"iteration":341,"passed_time":9.132431057,"remaining_time":1.094823606},
{"learn":[2136829.979],"iteration":342,"passed_time":9.160732535,"remaining_time":1.068307001},
{"learn":[2136142.077],"iteration":343,"passed_time":9.189272772,"remaining_time":1.041807087},
{"learn":[2135643.896],"iteration":344,"passed_time":9.215628074,"remaining_time":1.015054686},
{"learn":[2135068.004],"iteration":345,"passed_time":9.242927162,"remaining_time":0.9884055058},
{"learn":[2134823.825],"iteration":346,"passed_time":9.267900354,"remaining_time":0.9615112759},
{"learn":[2134294.069],"iteration":347,"passed_time":9.294467858,"remaining_time":0.934788434},
{"learn":[2133840.856],"iteration":348,"passed_time":9.321626957,"remaining_time":0.9081241162},
{"learn":[2133302.749],"iteration":349,"passed_time":9.347302697,"remaining_time":0.8813171114},
{"learn":[2132789.717],"iteration":350,"passed_time":9.373762284,"remaining_time":0.8545880145},
{"learn":[2132286.847],"iteration":351,"passed_time":9.3998545,"remaining_time":0.8278280951},
{"learn":[2131590.786],"iteration":352,"passed_time":9.427518379,"remaining_time":0.801205528},
{"learn":[2131135.793],"iteration":353,"passed_time":9.454194891,"remaining_time":0.7744961916},
{"learn":[2130407.429],"iteration":354,"passed_time":9.480568748,"remaining_time":0.7477631689},
{"learn":[2130144.316],"iteration":355,"passed_time":9.506063435,"remaining_time":0.7209654852},
{"learn":[2129583.767],"iteration":356,"passed_time":9.532706918,"remaining_time":0.6942587672},
{"learn":[2129203.818],"iteration":357,"passed_time":9.558538999,"remaining_time":0.6674957401},
{"learn":[2128644.196],"iteration":358,"passed_time":9.587517368,"remaining_time":0.6409482363},
{"learn":[2128237.384],"iteration":359,"passed_time":9.61511235,"remaining_time":0.6142988446},
{"learn":[2127370.339],"iteration":360,"passed_time":9.640708344,"remaining_time":0.5875223921},
{"learn":[2126827.815],"iteration":361,"passed_time":9.668032308,"remaining_time":0.560852703},
{"learn":[2126389.7],"iteration":362,"passed_time":9.695619015,"remaining_time":0.5341938851},
{"learn":[2125439.479],"iteration":363,"passed_time":9.723263434,"remaining_time":0.5075329815},
{"learn":[2125145.696],"iteration":364,"passed_time":9.749628914,"remaining_time":0.4808036177},
{"learn":[2124464.58],"iteration":365,"passed_time":9.777545504,"remaining_time":0.4541482885},
{"learn":[2123687.942],"iteration":366,"passed_time":9.805359544,"remaining_time":0.427481615},
{"learn":[2123029.395],"iteration":367,"passed_time":9.832923281,"remaining_time":0.4007985033},
{"learn":[2122558.605],"iteration":368,"passed_time":9.859936525,"remaining_time":0.3740897326},
{"learn":[2121799.088],"iteration":369,"passed_time":9.888548089,"remaining_time":0.3474354734},
{"learn":[2120713.318],"iteration":370,"passed_time":9.91586426,"remaining_time":0.3207287631},
{"learn":[2120171.586],"iteration":371,"passed_time":9.943411138,"remaining_time":0.2940255982},
{"learn":[2119459.283],"iteration":372,"passed_time":9.970811694,"remaining_time":0.2673139864},
{"learn":[2118677.989],"iteration":373,"passed_time":9.998163681,"remaining_time":0.2405975217},
{"learn":[2118210.705],"iteration":374,"passed_time":10.02572961,"remaining_time":0.2138822316},
{"learn":[2117827.833],"iteration":375,"passed_time":10.05181069,"remaining_time":0.1871347735},
{"learn":[2117248.608],"iteration":376,"passed_time":10.08053374,"remaining_time":0.1604328977},
{"learn":[2116289.677],"iteration":377,"passed_time":10.10983044,"remaining_time":0.1337279159},
{"learn":[2115506.208],"iteration":378,"passed_time":10.13894874,"remaining_time":0.1070073745},
{"learn":[2114997.487],"iteration":379,"passed_time":10.16645497,"remaining_time":0.0802614866},
{"learn":[2114438.572],"iteration":380,"passed_time":10.19206476,"remaining_time":0.0535016523},
{"learn":[2114017.4],"iteration":381,"passed_time":10.21858921,"remaining_time":0.02675023352},
{"learn":[2113318.549],"iteration":382,"passed_time":10.24606895,"remaining_time":0}
]}